{
  "12mK": {
    "antiwindup": true,
    "controller_ip": "localhost",
    "controller_timeout": 10.0,
    "d_smooth_points": 20,
    "dt": 9.0,
    "heater_channel": 4,
    "kd": 80000.0,
    "keep_integral_on_tune": true,
    "ki": 6.0,
    "kp": 2000.0,
    "reset_integral_on_start": true,
    "setpoint": 0.012,
    "temp_channel": 6,
    "u_ff": 2.9,
    "u_max": 8.0,
    "u_min": 0.0
  },
  "14mK": {
    "antiwindup": true,
    "controller_ip": "localhost",
    "controller_timeout": 10.0,
    "d_smooth_points": 16,
    "dt": 9.0,
    "heater_channel": 4,
    "kd": 100000.0,
    "keep_integral_on_tune": true,
    "ki": 5.0,
    "kp": 2000.0,
    "reset_integral_on_start": true,
    "setpoint": 0.014,
    "temp_channel": 6,
    "u_ff": 3.8,
    "u_max": 8.0,
    "u_min": 0.0
  }
}